{
	"info": {
		"_postman_id": "42c75138-4fee-495f-b844-568ee576748b",
		"name": "twitter",
		"schema": "https://schema.getpostman.com/json/collection/v2.1.0/collection.json"
	},
	"item": [
		{
			"name": "auth",
			"item": [
				{
					"name": "register",
					"request": {
						"method": "POST",
						"header": [
							{
								"key": "Content-Type",
								"name": "Content-Type",
								"value": "application/x-www-form-urlencoded",
								"type": "text"
							}
						],
						"body": {
							"mode": "urlencoded",
							"urlencoded": [
								{
									"key": "name",
									"value": "vasya",
									"type": "text"
								},
								{
									"key": "email",
									"value": "vasya@vasya.ru",
									"type": "text"
								},
								{
									"key": "password",
									"value": "131313",
									"type": "text"
								},
								{
									"key": "",
									"value": "",
									"type": "text"
								}
							]
						},
						"url": {
							"raw": "http://localhost:3000/auth/register",
							"protocol": "http",
							"host": [
								"localhost"
							],
							"port": "3000",
							"path": [
								"auth",
								"register"
							]
						}
					},
					"response": []
				},
				{
					"name": "auth",
					"request": {
						"method": "POST",
						"header": [
							{
								"key": "Content-Type",
								"name": "Content-Type",
								"value": "application/x-www-form-urlencoded",
								"type": "text"
							}
						],
						"body": {
							"mode": "urlencoded",
							"urlencoded": [
								{
									"key": "email",
									"value": "vasya@vasya.ru",
									"type": "text"
								},
								{
									"key": "password",
									"value": "131313",
									"type": "text"
								}
							]
						},
						"url": {
							"raw": "http://localhost:3000/auth/login",
							"protocol": "http",
							"host": [
								"localhost"
							],
							"port": "3000",
							"path": [
								"auth",
								"login"
							]
						}
					},
					"response": []
				},
				{
					"name": "me",
					"protocolProfileBehavior": {
						"disableBodyPruning": true
					},
					"request": {
						"method": "GET",
						"header": [
							{
								"key": "Content-Type",
								"name": "Content-Type",
								"value": "application/x-www-form-urlencoded",
								"type": "text"
							},
							{
								"key": "auth",
								"value": "eyJhbGciOiJIUzI1NiIsInR5cCI6IkpXVCJ9.eyJpZCI6MywiaWF0IjoxNTc3MTE1OTYyLCJleHAiOjE1NzcxNTE5NjJ9.K6_1p3V6YWfkFyPVgGXU3gPXG3czZc_Q1EgA25Uqhuo",
								"type": "text"
							}
						],
						"body": {
							"mode": "urlencoded",
							"urlencoded": []
						},
						"url": {
							"raw": "http://localhost:3000/auth/me",
							"protocol": "http",
							"host": [
								"localhost"
							],
							"port": "3000",
							"path": [
								"auth",
								"me"
							]
						}
					},
					"response": []
				}
			],
			"protocolProfileBehavior": {}
		},
		{
			"name": "user",
			"item": [
				{
					"name": "profile",
					"protocolProfileBehavior": {
						"disableBodyPruning": true
					},
					"request": {
						"method": "GET",
						"header": [
							{
								"key": "Content-Type",
								"name": "Content-Type",
								"type": "text",
								"value": "application/x-www-form-urlencoded"
							},
							{
								"key": "auth",
								"type": "text",
								"value": "eyJhbGciOiJIUzI1NiIsInR5cCI6IkpXVCJ9.eyJpZCI6MywiaWF0IjoxNTc3MTE1OTYyLCJleHAiOjE1NzcxNTE5NjJ9.K6_1p3V6YWfkFyPVgGXU3gPXG3czZc_Q1EgA25Uqhuo"
							}
						],
						"body": {
							"mode": "urlencoded",
							"urlencoded": []
						},
						"url": {
							"raw": "http://localhost:3000/user/profile",
							"protocol": "http",
							"host": [
								"localhost"
							],
							"port": "3000",
							"path": [
								"user",
								"profile"
							]
						}
					},
					"response": []
				},
				{
					"name": "update profile",
					"request": {
						"method": "POST",
						"header": [
							{
								"key": "Content-Type",
								"name": "Content-Type",
								"value": "application/x-www-form-urlencoded",
								"type": "text"
							},
							{
								"key": "auth",
								"value": "eyJhbGciOiJIUzI1NiIsInR5cCI6IkpXVCJ9.eyJpZCI6MywiaWF0IjoxNTc3MTE1OTYyLCJleHAiOjE1NzcxNTE5NjJ9.K6_1p3V6YWfkFyPVgGXU3gPXG3czZc_Q1EgA25Uqhuo",
								"type": "text"
							}
						],
						"body": {
							"mode": "urlencoded",
							"urlencoded": [
								{
									"key": "email",
									"value": "vasya@vasya.ru",
									"type": "text"
								},
								{
									"key": "password",
									"value": "1123123123",
									"type": "text"
								},
								{
									"key": "name",
									"value": "new vasya",
									"type": "text"
								}
							]
						},
						"url": {
							"raw": "http://localhost:3000/user",
							"protocol": "http",
							"host": [
								"localhost"
							],
							"port": "3000",
							"path": [
								"user"
							]
						}
					},
					"response": []
				}
			],
			"protocolProfileBehavior": {}
		},
		{
			"name": "tag",
			"item": [
				{
					"name": "create tag",
					"request": {
						"method": "POST",
						"header": [
							{
								"key": "Content-Type",
								"name": "Content-Type",
								"value": "application/x-www-form-urlencoded",
								"type": "text"
							},
							{
								"key": "auth",
								"value": "eyJhbGciOiJIUzI1NiIsInR5cCI6IkpXVCJ9.eyJpZCI6MywiaWF0IjoxNTc3MTE1OTYyLCJleHAiOjE1NzcxNTE5NjJ9.K6_1p3V6YWfkFyPVgGXU3gPXG3czZc_Q1EgA25Uqhuo",
								"type": "text"
							}
						],
						"body": {
							"mode": "urlencoded",
							"urlencoded": [
								{
									"key": "name",
									"value": "news",
									"type": "text"
								}
							]
						},
						"url": {
							"raw": "http://localhost:3000/tag",
							"protocol": "http",
							"host": [
								"localhost"
							],
							"port": "3000",
							"path": [
								"tag"
							]
						}
					},
					"response": []
				},
				{
					"name": "get tag by id",
					"protocolProfileBehavior": {
						"disableBodyPruning": true
					},
					"request": {
						"method": "GET",
						"header": [
							{
								"key": "Content-Type",
								"name": "Content-Type",
								"value": "application/x-www-form-urlencoded",
								"type": "text"
							},
							{
								"key": "auth",
								"value": "eyJhbGciOiJIUzI1NiIsInR5cCI6IkpXVCJ9.eyJpZCI6MiwiaWF0IjoxNTc3MTE5MDIyLCJleHAiOjE1NzcxNTUwMjJ9.vWixYr8dPzGg8dMmz8n3xYV_HhhQRjGMyFUnc7IUl8A",
								"type": "text"
							}
						],
						"body": {
							"mode": "urlencoded",
							"urlencoded": []
						},
						"url": {
							"raw": "http://localhost:3000/tag/1",
							"protocol": "http",
							"host": [
								"localhost"
							],
							"port": "3000",
							"path": [
								"tag",
								"1"
							]
						}
					},
					"response": []
				}
			],
			"protocolProfileBehavior": {}
		},
		{
			"name": "twit",
			"item": [
				{
					"name": "create twit",
					"request": {
						"method": "POST",
						"header": [
							{
								"key": "Content-Type",
								"name": "Content-Type",
								"value": "application/x-www-form-urlencoded",
								"type": "text"
							},
							{
								"key": "auth",
								"value": "eyJhbGciOiJIUzI1NiIsInR5cCI6IkpXVCJ9.eyJpZCI6MywiaWF0IjoxNTc3MTE1OTYyLCJleHAiOjE1NzcxNTE5NjJ9.K6_1p3V6YWfkFyPVgGXU3gPXG3czZc_Q1EgA25Uqhuo",
								"type": "text"
							}
						],
						"body": {
							"mode": "urlencoded",
							"urlencoded": [
								{
									"key": "text",
									"value": "some twit text123",
									"type": "text"
								},
								{
									"key": "tags",
									"value": "tag1asdasdas;taglala;tahUsjks",
									"type": "text"
								}
							]
						},
						"url": {
							"raw": "http://localhost:3000/twit",
							"protocol": "http",
							"host": [
								"localhost"
							],
							"port": "3000",
							"path": [
								"twit"
							]
						}
					},
					"response": []
				},
				{
					"name": "update twit",
					"request": {
						"method": "POST",
						"header": [
							{
								"key": "Content-Type",
								"name": "Content-Type",
								"type": "text",
								"value": "application/x-www-form-urlencoded"
							},
							{
								"key": "auth",
								"type": "text",
								"value": "eyJhbGciOiJIUzI1NiIsInR5cCI6IkpXVCJ9.eyJpZCI6MywiaWF0IjoxNTc3MTE1OTYyLCJleHAiOjE1NzcxNTE5NjJ9.K6_1p3V6YWfkFyPVgGXU3gPXG3czZc_Q1EgA25Uqhuo"
							}
						],
						"body": {
							"mode": "urlencoded",
							"urlencoded": [
								{
									"key": "text",
									"value": "some twit text123",
									"type": "text"
								},
								{
									"key": "tags",
									"value": "tag1asdas;das;taglala;tahUsjks",
									"type": "text"
								}
							]
						},
						"url": {
							"raw": "http://localhost:3000/twit/1",
							"protocol": "http",
							"host": [
								"localhost"
							],
							"port": "3000",
							"path": [
								"twit",
								"1"
							]
						}
					},
					"response": []
				},
				{
					"name": "get twit by id",
					"protocolProfileBehavior": {
						"disableBodyPruning": true
					},
					"request": {
						"method": "GET",
						"header": [
							{
								"key": "Content-Type",
								"name": "Content-Type",
								"value": "application/x-www-form-urlencoded",
								"type": "text"
							},
							{
								"key": "auth",
								"value": "eyJhbGciOiJIUzI1NiIsInR5cCI6IkpXVCJ9.eyJpZCI6MywiaWF0IjoxNTc3MTE1OTYyLCJleHAiOjE1NzcxNTE5NjJ9.K6_1p3V6YWfkFyPVgGXU3gPXG3czZc_Q1EgA25Uqhuo",
								"type": "text"
							}
						],
						"body": {
							"mode": "urlencoded",
							"urlencoded": []
						},
						"url": {
							"raw": "http://localhost:3000/twit/1",
							"protocol": "http",
							"host": [
								"localhost"
							],
							"port": "3000",
							"path": [
								"twit",
								"1"
							]
						}
					},
					"response": []
				},
				{
					"name": "get twits",
					"protocolProfileBehavior": {
						"disableBodyPruning": true
					},
					"request": {
						"method": "GET",
						"header": [
							{
								"key": "Content-Type",
								"name": "Content-Type",
								"type": "text",
								"value": "application/x-www-form-urlencoded"
							},
							{
								"key": "auth",
								"type": "text",
								"value": "eyJhbGciOiJIUzI1NiIsInR5cCI6IkpXVCJ9.eyJpZCI6MiwiaWF0IjoxNTc3MTE5MDIyLCJleHAiOjE1NzcxNTUwMjJ9.vWixYr8dPzGg8dMmz8n3xYV_HhhQRjGMyFUnc7IUl8A"
							}
						],
						"body": {
							"mode": "urlencoded",
							"urlencoded": []
						},
						"url": {
							"raw": "http://localhost:3000/twit/twits?q=solid&order=ASC&page=1&take=10&create_date_start=2019-12-21T14:48:00&create_date_end=2019-12-25T14:48:00&tags=Refined Wooden Tuna;Awesome Cotton Chair",
							"protocol": "http",
							"host": [
								"localhost"
							],
							"port": "3000",
							"path": [
								"twit",
								"twits"
							],
							"query": [
								{
									"key": "q",
									"value": "solid"
								},
								{
									"key": "order",
									"value": "ASC"
								},
								{
									"key": "page",
									"value": "1"
								},
								{
									"key": "take",
									"value": "10"
								},
								{
									"key": "create_date_start",
									"value": "2019-12-21T14:48:00"
								},
								{
									"key": "create_date_end",
									"value": "2019-12-25T14:48:00"
								},
								{
									"key": "tags",
									"value": "Refined Wooden Tuna;Awesome Cotton Chair"
								}
							]
						}
					},
					"response": []
				}
			],
			"protocolProfileBehavior": {}
		}
	],
	"protocolProfileBehavior": {}
}